gocqapi/__init__.py
gocqapi/_api.py
gocqapi/group_manage.py
gocqapi/info.py
gocqapi/message.py
gocqapi/models.py
gocqapi/self_manage.py
gocqapi-0.1.6.dist-info/LICENSE
gocqapi-0.1.6.dist-info/WHEEL
gocqapi-0.1.6.dist-info/METADATA
gocqapi-0.1.6.dist-info/RECORD
