Metadata-Version: 2.1
Name: gocqapi
Version: 0.1.6
Summary: go-cqhttp API typing annoations, return data models and utils for nonebot
License: MIT
Author: 风屿
Author-email: i@windis.cn
Requires-Python: >=3.7.3,<4.0.0
Classifier: License :: OSI Approved :: MIT License
Classifier: Programming Language :: Python :: 3
Classifier: Programming Language :: Python :: 3.8
Classifier: Programming Language :: Python :: 3.9
Classifier: Programming Language :: Python :: 3.10
Requires-Dist: httpx (>=0.23.0,<0.24.0)
Requires-Dist: nonebot-adapter-onebot (>=2.1.3,<3.0.0)
Requires-Dist: nonebot2 (>=2.0.0-beta.5,<3.0.0)
Requires-Dist: pydantic (>=1.9.0,<2.0.0)
